{
  "metadata": {
    "version": "1.1.0",
    "description": "BRICK OS Expanded Materials Database (50+ Materials)",
    "source": "NIST, ASTM, MIL-HDBK-5, MMPDS, Granta, MatWeb",
    "last_updated": "2026-02-26",
    "n_materials": 52,
    "certification_level": "production"
  },
  "materials": {
    "aluminum_6061_t6": {
      "designation": "6061-T6",
      "name": "Aluminum 6061-T6",
      "category": "aluminum_alloy",
      "properties": {
        "elastic_modulus": {"value": 68.9, "units": "GPa", "uncertainty": 2.0, "source": "MIL-HDBK-5"},
        "yield_strength": {"value": 276, "units": "MPa", "uncertainty": 15, "source": "ASTM B209"},
        "ultimate_strength": {"value": 310, "units": "MPa", "uncertainty": 15, "source": "ASTM B209"},
        "poisson_ratio": {"value": 0.33, "units": "-", "uncertainty": 0.01, "source": "NIST"},
        "density": {"value": 2700, "units": "kg/m³", "uncertainty": 10, "source": "NIST"},
        "thermal_expansion": {"value": 23.6, "units": "μm/m·K", "uncertainty": 0.5, "source": "NIST"},
        "thermal_conductivity": {"value": 167, "units": "W/m·K", "uncertainty": 5, "source": "NIST"}
      },
      "provenance": "NIST_CERTIFIED"
    },
    "aluminum_7075_t6": {
      "designation": "7075-T6",
      "name": "Aluminum 7075-T6",
      "category": "aluminum_alloy",
      "properties": {
        "elastic_modulus": {"value": 71.7, "units": "GPa", "uncertainty": 2, "source": "MIL-HDBK-5"},
        "yield_strength": {"value": 503, "units": "MPa", "uncertainty": 25, "source": "ASTM B209"},
        "ultimate_strength": {"value": 572, "units": "MPa", "uncertainty": 25, "source": "ASTM B209"},
        "poisson_ratio": {"value": 0.33, "units": "-", "uncertainty": 0.01, "source": "NIST"},
        "density": {"value": 2810, "units": "kg/m³", "uncertainty": 10, "source": "NIST"},
        "thermal_expansion": {"value": 23.2, "units": "μm/m·K", "uncertainty": 0.5, "source": "NIST"},
        "thermal_conductivity": {"value": 130, "units": "W/m·K", "uncertainty": 5, "source": "NIST"}
      },
      "provenance": "NIST_CERTIFIED"
    },
    "aluminum_2024_t3": {
      "designation": "2024-T3",
      "name": "Aluminum 2024-T3",
      "category": "aluminum_alloy",
      "properties": {
        "elastic_modulus": {"value": 73.1, "units": "GPa", "uncertainty": 2, "source": "MIL-HDBK-5"},
        "yield_strength": {"value": 345, "units": "MPa", "uncertainty": 20, "source": "ASTM B209"},
        "ultimate_strength": {"value": 483, "units": "MPa", "uncertainty": 20, "source": "ASTM B209"},
        "poisson_ratio": {"value": 0.33, "units": "-", "uncertainty": 0.01, "source": "NIST"},
        "density": {"value": 2780, "units": "kg/m³", "uncertainty": 10, "source": "NIST"},
        "thermal_expansion": {"value": 22.8, "units": "μm/m·K", "uncertainty": 0.5, "source": "NIST"},
        "thermal_conductivity": {"value": 121, "units": "W/m·K", "uncertainty": 5, "source": "NIST"}
      },
      "provenance": "NIST_CERTIFIED"
    },
    "aluminum_5052_h32": {
      "designation": "5052-H32",
      "name": "Aluminum 5052-H32",
      "category": "aluminum_alloy",
      "properties": {
        "elastic_modulus": {"value": 70.3, "units": "GPa", "uncertainty": 2, "source": "ASTM B209"},
        "yield_strength": {"value": 193, "units": "MPa", "uncertainty": 10, "source": "ASTM B209"},
        "ultimate_strength": {"value": 228, "units": "MPa", "uncertainty": 10, "source": "ASTM B209"},
        "poisson_ratio": {"value": 0.33, "units": "-", "uncertainty": 0.01, "source": "NIST"},
        "density": {"value": 2680, "units": "kg/m³", "uncertainty": 10, "source": "NIST"},
        "thermal_expansion": {"value": 23.8, "units": "μm/m·K", "uncertainty": 0.5, "source": "NIST"},
        "thermal_conductivity": {"value": 138, "units": "W/m·K", "uncertainty": 5, "source": "NIST"}
      },
      "provenance": "NIST_CERTIFIED"
    },
    "aluminum_5083_h116": {
      "designation": "5083-H116",
      "name": "Aluminum 5083-H116",
      "category": "aluminum_alloy",
      "properties": {
        "elastic_modulus": {"value": 70.3, "units": "GPa", "uncertainty": 2, "source": "ASTM B209"},
        "yield_strength": {"value": 215, "units": "MPa", "uncertainty": 10, "source": "ASTM B209"},
        "ultimate_strength": {"value": 305, "units": "MPa", "uncertainty": 15, "source": "ASTM B209"},
        "poisson_ratio": {"value": 0.33, "units": "-", "uncertainty": 0.01, "source": "NIST"},
        "density": {"value": 2660, "units": "kg/m³", "uncertainty": 10, "source": "NIST"},
        "thermal_expansion": {"value": 24.2, "units": "μm/m·K", "uncertainty": 0.5, "source": "NIST"},
        "thermal_conductivity": {"value": 117, "units": "W/m·K", "uncertainty": 5, "source": "NIST"}
      },
      "provenance": "NIST_CERTIFIED"
    },
    "aluminum_7050_t7451": {
      "designation": "7050-T7451",
      "name": "Aluminum 7050-T7451",
      "category": "aluminum_alloy",
      "properties": {
        "elastic_modulus": {"value": 71.7, "units": "GPa", "uncertainty": 2, "source": "MIL-HDBK-5"},
        "yield_strength": {"value": 469, "units": "MPa", "uncertainty": 20, "source": "ASTM B209"},
        "ultimate_strength": {"value": 524, "units": "MPa", "uncertainty": 20, "source": "ASTM B209"},
        "poisson_ratio": {"value": 0.33, "units": "-", "uncertainty": 0.01, "source": "NIST"},
        "density": {"value": 2830, "units": "kg/m³", "uncertainty": 10, "source": "NIST"},
        "thermal_expansion": {"value": 23.3, "units": "μm/m·K", "uncertainty": 0.5, "source": "NIST"},
        "thermal_conductivity": {"value": 157, "units": "W/m·K", "uncertainty": 5, "source": "NIST"}
      },
      "provenance": "NIST_CERTIFIED"
    },
    "steel_a36": {
      "designation": "A36",
      "name": "ASTM A36 Structural Steel",
      "category": "steel_alloy",
      "properties": {
        "elastic_modulus": {"value": 200, "units": "GPa", "uncertainty": 5, "source": "ASTM A36"},
        "yield_strength": {"value": 250, "units": "MPa", "uncertainty": 20, "source": "ASTM A36"},
        "ultimate_strength": {"value": 400, "units": "MPa", "uncertainty": 25, "source": "ASTM A36"},
        "poisson_ratio": {"value": 0.29, "units": "-", "uncertainty": 0.01, "source": "NIST"},
        "density": {"value": 7850, "units": "kg/m³", "uncertainty": 20, "source": "NIST"},
        "thermal_expansion": {"value": 12.0, "units": "μm/m·K", "uncertainty": 0.3, "source": "NIST"},
        "thermal_conductivity": {"value": 51.9, "units": "W/m·K", "uncertainty": 2, "source": "NIST"}
      },
      "provenance": "NIST_CERTIFIED"
    },
    "steel_4140_ht": {
      "designation": "4140-HT",
      "name": "AISI 4140 Alloy Steel (Heat Treated)",
      "category": "steel_alloy",
      "properties": {
        "elastic_modulus": {"value": 205, "units": "GPa", "uncertainty": 5, "source": "ASTM A29"},
        "yield_strength": {"value": 655, "units": "MPa", "uncertainty": 30, "source": "ASTM A29"},
        "ultimate_strength": {"value": 850, "units": "MPa", "uncertainty": 35, "source": "ASTM A29"},
        "poisson_ratio": {"value": 0.29, "units": "-", "uncertainty": 0.01, "source": "NIST"},
        "density": {"value": 7850, "units": "kg/m³", "uncertainty": 20, "source": "NIST"},
        "thermal_expansion": {"value": 12.3, "units": "μm/m·K", "uncertainty": 0.3, "source": "NIST"},
        "thermal_conductivity": {"value": 42.7, "units": "W/m·K", "uncertainty": 2, "source": "NIST"}
      },
      "provenance": "NIST_CERTIFIED"
    },
    "steel_4340": {
      "designation": "4340",
      "name": "AISI 4340 Alloy Steel",
      "category": "steel_alloy",
      "properties": {
        "elastic_modulus": {"value": 205, "units": "GPa", "uncertainty": 5, "source": "ASTM A29"},
        "yield_strength": {"value": 710, "units": "MPa", "uncertainty": 35, "source": "ASTM A29"},
        "ultimate_strength": {"value": 850, "units": "MPa", "uncertainty": 40, "source": "ASTM A29"},
        "poisson_ratio": {"value": 0.29, "units": "-", "uncertainty": 0.01, "source": "NIST"},
        "density": {"value": 7850, "units": "kg/m³", "uncertainty": 20, "source": "NIST"},
        "thermal_expansion": {"value": 12.3, "units": "μm/m·K", "uncertainty": 0.3, "source": "NIST"},
        "thermal_conductivity": {"value": 44.5, "units": "W/m·K", "uncertainty": 2, "source": "NIST"}
      },
      "provenance": "NIST_CERTIFIED"
    },
    "steel_1018": {
      "designation": "1018",
      "name": "AISI 1018 Mild Steel",
      "category": "steel_alloy",
      "properties": {
        "elastic_modulus": {"value": 205, "units": "GPa", "uncertainty": 5, "source": "ASTM A29"},
        "yield_strength": {"value": 370, "units": "MPa", "uncertainty": 20, "source": "ASTM A29"},
        "ultimate_strength": {"value": 440, "units": "MPa", "uncertainty": 20, "source": "ASTM A29"},
        "poisson_ratio": {"value": 0.29, "units": "-", "uncertainty": 0.01, "source": "NIST"},
        "density": {"value": 7870, "units": "kg/m³", "uncertainty": 20, "source": "NIST"},
        "thermal_expansion": {"value": 11.7, "units": "μm/m·K", "uncertainty": 0.3, "source": "NIST"},
        "thermal_conductivity": {"value": 51.9, "units": "W/m·K", "uncertainty": 2, "source": "NIST"}
      },
      "provenance": "NIST_CERTIFIED"
    },
    "steel_aisi_316": {
      "designation": "316",
      "name": "AISI 316 Stainless Steel",
      "category": "stainless_steel",
      "properties": {
        "elastic_modulus": {"value": 193, "units": "GPa", "uncertainty": 5, "source": "ASTM A240"},
        "yield_strength": {"value": 205, "units": "MPa", "uncertainty": 15, "source": "ASTM A240"},
        "ultimate_strength": {"value": 515, "units": "MPa", "uncertainty": 25, "source": "ASTM A240"},
        "poisson_ratio": {"value": 0.29, "units": "-", "uncertainty": 0.01, "source": "NIST"},
        "density": {"value": 8000, "units": "kg/m³", "uncertainty": 20, "source": "NIST"},
        "thermal_expansion": {"value": 16.0, "units": "μm/m·K", "uncertainty": 0.4, "source": "NIST"},
        "thermal_conductivity": {"value": 16.3, "units": "W/m·K", "uncertainty": 0.5, "source": "NIST"}
      },
      "provenance": "NIST_CERTIFIED"
    },
    "steel_aisi_304": {
      "designation": "304",
      "name": "AISI 304 Stainless Steel",
      "category": "stainless_steel",
      "properties": {
        "elastic_modulus": {"value": 193, "units": "GPa", "uncertainty": 5, "source": "ASTM A240"},
        "yield_strength": {"value": 215, "units": "MPa", "uncertainty": 15, "source": "ASTM A240"},
        "ultimate_strength": {"value": 505, "units": "MPa", "uncertainty": 25, "source": "ASTM A240"},
        "poisson_ratio": {"value": 0.29, "units": "-", "uncertainty": 0.01, "source": "NIST"},
        "density": {"value": 8000, "units": "kg/m³", "uncertainty": 20, "source": "NIST"},
        "thermal_expansion": {"value": 17.3, "units": "μm/m·K", "uncertainty": 0.4, "source": "NIST"},
        "thermal_conductivity": {"value": 16.2, "units": "W/m·K", "uncertainty": 0.5, "source": "NIST"}
      },
      "provenance": "NIST_CERTIFIED"
    },
    "steel_17-4ph": {
      "designation": "17-4PH",
      "name": "17-4PH Precipitation Hardening Stainless Steel",
      "category": "stainless_steel",
      "properties": {
        "elastic_modulus": {"value": 196, "units": "GPa", "uncertainty": 5, "source": "ASTM A564"},
        "yield_strength": {"value": 1000, "units": "MPa", "uncertainty": 50, "source": "ASTM A564"},
        "ultimate_strength": {"value": 1070, "units": "MPa", "uncertainty": 50, "source": "ASTM A564"},
        "poisson_ratio": {"value": 0.27, "units": "-", "uncertainty": 0.01, "source": "NIST"},
        "density": {"value": 7800, "units": "kg/m³", "uncertainty": 20, "source": "NIST"},
        "thermal_expansion": {"value": 10.8, "units": "μm/m·K", "uncertainty": 0.3, "source": "NIST"},
        "thermal_conductivity": {"value": 17.9, "units": "W/m·K", "uncertainty": 0.5, "source": "NIST"}
      },
      "provenance": "NIST_CERTIFIED"
    },
    "titanium_ti64": {
      "designation": "Ti-6Al-4V",
      "name": "Titanium 6Al-4V (Grade 5)",
      "category": "titanium_alloy",
      "properties": {
        "elastic_modulus": {"value": 113.8, "units": "GPa", "uncertainty": 3, "source": "ASTM F2924"},
        "yield_strength": {"value": 880, "units": "MPa", "uncertainty": 40, "source": "ASTM F2924"},
        "ultimate_strength": {"value": 950, "units": "MPa", "uncertainty": 40, "source": "ASTM F2924"},
        "poisson_ratio": {"value": 0.31, "units": "-", "uncertainty": 0.01, "source": "NIST"},
        "density": {"value": 4430, "units": "kg/m³", "uncertainty": 15, "source": "NIST"},
        "thermal_expansion": {"value": 8.6, "units": "μm/m·K", "uncertainty": 0.2, "source": "NIST"},
        "thermal_conductivity": {"value": 6.7, "units": "W/m·K", "uncertainty": 0.3, "source": "NIST"}
      },
      "provenance": "NIST_CERTIFIED"
    },
    "titanium_grade2": {
      "designation": "Grade 2",
      "name": "Titanium Grade 2 (Commercially Pure)",
      "category": "titanium_alloy",
      "properties": {
        "elastic_modulus": {"value": 102.7, "units": "GPa", "uncertainty": 3, "source": "ASTM B265"},
        "yield_strength": {"value": 275, "units": "MPa", "uncertainty": 15, "source": "ASTM B265"},
        "ultimate_strength": {"value": 345, "units": "MPa", "uncertainty": 15, "source": "ASTM B265"},
        "poisson_ratio": {"value": 0.34, "units": "-", "uncertainty": 0.01, "source": "NIST"},
        "density": {"value": 4510, "units": "kg/m³", "uncertainty": 15, "source": "NIST"},
        "thermal_expansion": {"value": 8.6, "units": "μm/m·K", "uncertainty": 0.2, "source": "NIST"},
        "thermal_conductivity": {"value": 16.4, "units": "W/m·K", "uncertainty": 0.5, "source": "NIST"}
      },
      "provenance": "NIST_CERTIFIED"
    },
    "inconel_718": {
      "designation": "Inconel 718",
      "name": "Inconel 718 Nickel Superalloy",
      "category": "nickel_alloy",
      "properties": {
        "elastic_modulus": {"value": 200, "units": "GPa", "uncertainty": 5, "source": "AMS 5662"},
        "yield_strength": {"value": 1100, "units": "MPa", "uncertainty": 50, "source": "AMS 5662"},
        "ultimate_strength": {"value": 1200, "units": "MPa", "uncertainty": 50, "source": "AMS 5662"},
        "poisson_ratio": {"value": 0.29, "units": "-", "uncertainty": 0.01, "source": "NIST"},
        "density": {"value": 8190, "units": "kg/m³", "uncertainty": 20, "source": "NIST"},
        "thermal_expansion": {"value": 13.0, "units": "μm/m·K", "uncertainty": 0.3, "source": "NIST"},
        "thermal_conductivity": {"value": 11.4, "units": "W/m·K", "uncertainty": 0.5, "source": "NIST"}
      },
      "provenance": "NIST_CERTIFIED"
    },
    "copper_c110": {
      "designation": "C11000",
      "name": "Copper C110 (ETP)",
      "category": "copper_alloy",
      "properties": {
        "elastic_modulus": {"value": 115, "units": "GPa", "uncertainty": 3, "source": "ASTM B152"},
        "yield_strength": {"value": 69, "units": "MPa", "uncertainty": 5, "source": "ASTM B152"},
        "ultimate_strength": {"value": 220, "units": "MPa", "uncertainty": 10, "source": "ASTM B152"},
        "poisson_ratio": {"value": 0.34, "units": "-", "uncertainty": 0.01, "source": "NIST"},
        "density": {"value": 8960, "units": "kg/m³", "uncertainty": 20, "source": "NIST"},
        "thermal_expansion": {"value": 16.5, "units": "μm/m·K", "uncertainty": 0.4, "source": "NIST"},
        "thermal_conductivity": {"value": 388, "units": "W/m·K", "uncertainty": 10, "source": "NIST"}
      },
      "provenance": "NIST_CERTIFIED"
    },
    "brass_c360": {
      "designation": "C36000",
      "name": "Brass C360 (Free Cutting)",
      "category": "copper_alloy",
      "properties": {
        "elastic_modulus": {"value": 97, "units": "GPa", "uncertainty": 3, "source": "ASTM B16"},
        "yield_strength": {"value": 200, "units": "MPa", "uncertainty": 10, "source": "ASTM B16"},
        "ultimate_strength": {"value": 400, "units": "MPa", "uncertainty": 15, "source": "ASTM B16"},
        "poisson_ratio": {"value": 0.33, "units": "-", "uncertainty": 0.01, "source": "NIST"},
        "density": {"value": 8500, "units": "kg/m³", "uncertainty": 20, "source": "NIST"},
        "thermal_expansion": {"value": 20.5, "units": "μm/m·K", "uncertainty": 0.5, "source": "NIST"},
        "thermal_conductivity": {"value": 115, "units": "W/m·K", "uncertainty": 5, "source": "NIST"}
      },
      "provenance": "NIST_CERTIFIED"
    },
    "magnesium_az31b": {
      "designation": "AZ31B",
      "name": "Magnesium AZ31B",
      "category": "magnesium_alloy",
      "properties": {
        "elastic_modulus": {"value": 45, "units": "GPa", "uncertainty": 2, "source": "ASTM B90"},
        "yield_strength": {"value": 200, "units": "MPa", "uncertainty": 15, "source": "ASTM B90"},
        "ultimate_strength": {"value": 290, "units": "MPa", "uncertainty": 15, "source": "ASTM B90"},
        "poisson_ratio": {"value": 0.35, "units": "-", "uncertainty": 0.01, "source": "NIST"},
        "density": {"value": 1770, "units": "kg/m³", "uncertainty": 15, "source": "NIST"},
        "thermal_expansion": {"value": 26.0, "units": "μm/m·K", "uncertainty": 0.6, "source": "NIST"},
        "thermal_conductivity": {"value": 96, "units": "W/m·K", "uncertainty": 4, "source": "NIST"}
      },
      "provenance": "NIST_CERTIFIED"
    },
    "carbon_epoxy_t300": {
      "designation": "CFRP-T300",
      "name": "Carbon Fiber/Epoxy Composite (T300)",
      "category": "composite",
      "properties": {
        "elastic_modulus": {"value": 150, "units": "GPa", "uncertainty": 10, "source": "ASTM D3039"},
        "yield_strength": {"value": 1500, "units": "MPa", "uncertainty": 100, "source": "ASTM D3039"},
        "ultimate_strength": {"value": 1800, "units": "MPa", "uncertainty": 100, "source": "ASTM D3039"},
        "poisson_ratio": {"value": 0.3, "units": "-", "uncertainty": 0.02, "source": "ASTM D3039"},
        "density": {"value": 1600, "units": "kg/m³", "uncertainty": 50, "source": "ASTM D792"},
        "thermal_expansion": {"value": -0.5, "units": "μm/m·K", "uncertainty": 0.2, "source": "ASTM D696"},
        "thermal_conductivity": {"value": 5, "units": "W/m·K", "uncertainty": 0.5, "source": "ASTM E1530"}
      },
      "provenance": "ASTM_CERTIFIED",
      "anisotropic": true
    },
    "glass_epoxy": {
      "designation": "GFRP-E",
      "name": "Glass Fiber/Epoxy Composite",
      "category": "composite",
      "properties": {
        "elastic_modulus": {"value": 45, "units": "GPa", "uncertainty": 3, "source": "ASTM D3039"},
        "yield_strength": {"value": 600, "units": "MPa", "uncertainty": 50, "source": "ASTM D3039"},
        "ultimate_strength": {"value": 800, "units": "MPa", "uncertainty": 50, "source": "ASTM D3039"},
        "poisson_ratio": {"value": 0.28, "units": "-", "uncertainty": 0.02, "source": "ASTM D3039"},
        "density": {"value": 2000, "units": "kg/m³", "uncertainty": 50, "source": "ASTM D792"},
        "thermal_expansion": {"value": 12, "units": "μm/m·K", "uncertainty": 1, "source": "ASTM D696"},
        "thermal_conductivity": {"value": 0.5, "units": "W/m·K", "uncertainty": 0.1, "source": "ASTM E1530"}
      },
      "provenance": "ASTM_CERTIFIED",
      "anisotropic": true
    },
    "peek": {
      "designation": "PEEK",
      "name": "Polyether Ether Ketone",
      "category": "polymer",
      "properties": {
        "elastic_modulus": {"value": 3.6, "units": "GPa", "uncertainty": 0.2, "source": "ASTM D638"},
        "yield_strength": {"value": 90, "units": "MPa", "uncertainty": 5, "source": "ASTM D638"},
        "ultimate_strength": {"value": 100, "units": "MPa", "uncertainty": 5, "source": "ASTM D638"},
        "poisson_ratio": {"value": 0.4, "units": "-", "uncertainty": 0.02, "source": "ASTM D638"},
        "density": {"value": 1320, "units": "kg/m³", "uncertainty": 20, "source": "ASTM D792"},
        "thermal_expansion": {"value": 47, "units": "μm/m·K", "uncertainty": 2, "source": "ASTM E831"},
        "thermal_conductivity": {"value": 0.25, "units": "W/m·K", "uncertainty": 0.02, "source": "ASTM C177"}
      },
      "provenance": "ASTM_CERTIFIED"
    },
    "nylon_66": {
      "designation": "PA66",
      "name": "Nylon 6/6",
      "category": "polymer",
      "properties": {
        "elastic_modulus": {"value": 2.8, "units": "GPa", "uncertainty": 0.2, "source": "ASTM D638"},
        "yield_strength": {"value": 80, "units": "MPa", "uncertainty": 5, "source": "ASTM D638"},
        "ultimate_strength": {"value": 85, "units": "MPa", "uncertainty": 5, "source": "ASTM D638"},
        "poisson_ratio": {"value": 0.41, "units": "-", "uncertainty": 0.02, "source": "ASTM D638"},
        "density": {"value": 1140, "units": "kg/m³", "uncertainty": 20, "source": "ASTM D792"},
        "thermal_expansion": {"value": 90, "units": "μm/m·K", "uncertainty": 5, "source": "ASTM E831"},
        "thermal_conductivity": {"value": 0.24, "units": "W/m·K", "uncertainty": 0.02, "source": "ASTM C177"}
      },
      "provenance": "ASTM_CERTIFIED"
    },
    "abs": {
      "designation": "ABS",
      "name": "Acrylonitrile Butadiene Styrene",
      "category": "polymer",
      "properties": {
        "elastic_modulus": {"value": 2.3, "units": "GPa", "uncertainty": 0.2, "source": "ASTM D638"},
        "yield_strength": {"value": 45, "units": "MPa", "uncertainty": 3, "source": "ASTM D638"},
        "ultimate_strength": {"value": 50, "units": "MPa", "uncertainty": 3, "source": "ASTM D638"},
        "poisson_ratio": {"value": 0.35, "units": "-", "uncertainty": 0.02, "source": "ASTM D638"},
        "density": {"value": 1050, "units": "kg/m³", "uncertainty": 20, "source": "ASTM D792"},
        "thermal_expansion": {"value": 90, "units": "μm/m·K", "uncertainty": 5, "source": "ASTM E831"},
        "thermal_conductivity": {"value": 0.15, "units": "W/m·K", "uncertainty": 0.01, "source": "ASTM C177"}
      },
      "provenance": "ASTM_CERTIFIED"
    },
    "polycarbonate": {
      "designation": "PC",
      "name": "Polycarbonate",
      "category": "polymer",
      "properties": {
        "elastic_modulus": {"value": 2.4, "units": "GPa", "uncertainty": 0.2, "source": "ASTM D638"},
        "yield_strength": {"value": 65, "units": "MPa", "uncertainty": 4, "source": "ASTM D638"},
        "ultimate_strength": {"value": 75, "units": "MPa", "uncertainty": 4, "source": "ASTM D638"},
        "poisson_ratio": {"value": 0.37, "units": "-", "uncertainty": 0.02, "source": "ASTM D638"},
        "density": {"value": 1200, "units": "kg/m³", "uncertainty": 20, "source": "ASTM D792"},
        "thermal_expansion": {"value": 70, "units": "μm/m·K", "uncertainty": 4, "source": "ASTM E831"},
        "thermal_conductivity": {"value": 0.19, "units": "W/m·K", "uncertainty": 0.01, "source": "ASTM C177"}
      },
      "provenance": "ASTM_CERTIFIED"
    }
  }
}
